pat/__init__.py
pat/__main__.py
pat/init.py
pat/main.py
pat/pat.py
pat/utils.py
Pat-0.5.3.dist-info/LICENSE.txt
Pat-0.5.3.dist-info/METADATA
Pat-0.5.3.dist-info/WHEEL
Pat-0.5.3.dist-info/entry_points.txt
Pat-0.5.3.dist-info/top_level.txt
Pat-0.5.3.dist-info/RECORD
